{
  "bids": [
    {
      "price": 111440,
      "amount": 12.1,
      "total": 12.1
    },
    {
      "price": 111430,
      "amount": 34.9,
      "total": 47.1
    },
    {
      "price": 111420,
      "amount": 11.5,
      "total": 58.5
    },
    {
      "price": 111410,
      "amount": 11.3,
      "total": 69.9
    },
    {
      "price": 111400,
      "amount": 28.2,
      "total": 98.0
    },
    {
      "price": 111390,
      "amount": 15.2,
      "total": 113.3
    },
    {
      "price": 111380,
      "amount": 37.8,
      "total": 151.1
    },
    {
      "price": 111370,
      "amount": 39.3,
      "total": 190.4
    },
    {
      "price": 111360,
      "amount": 38.8,
      "total": 229.2
    },
    {
      "price": 111350,
      "amount": 47.8,
      "total": 277.0
    },
    {
      "price": 111340,
      "amount": 53.2,
      "total": 330.2
    },
    {
      "price": 111330,
      "amount": 35.7,
      "total": 366.0
    },
    {
      "price": 111320,
      "amount": 32.8,
      "total": 398.8
    },
    {
      "price": 111310,
      "amount": 36.6,
      "total": 435.4
    },
    {
      "price": 111300,
      "amount": 20.1,
      "total": 455.5
    },
    {
      "price": 111290,
      "amount": 30.2,
      "total": 485.6
    },
    {
      "price": 111280,
      "amount": 33.6,
      "total": 519.3
    },
    {
      "price": 111270,
      "amount": 37.9,
      "total": 557.2
    },
    {
      "price": 111260,
      "amount": 29.4,
      "total": 586.5
    },
    {
      "price": 111250,
      "amount": 78.7,
      "total": 665.3
    },
    {
      "price": 111240,
      "amount": 53.7,
      "total": 719.0
    },
    {
      "price": 111230,
      "amount": 26.3,
      "total": 745.4
    },
    {
      "price": 111220,
      "amount": 24.8,
      "total": 770.1
    },
    {
      "price": 111210,
      "amount": 69.1,
      "total": 839.2
    },
    {
      "price": 111200,
      "amount": 32.1,
      "total": 871.3
    },
    {
      "price": 111190,
      "amount": 34.6,
      "total": 905.9
    },
    {
      "price": 111180,
      "amount": 64.5,
      "total": 970.4
    },
    {
      "price": 111170,
      "amount": 19.2,
      "total": 989.6
    },
    {
      "price": 111160,
      "amount": 30.5,
      "total": 1020
    },
    {
      "price": 111150,
      "amount": 14.4,
      "total": 1034
    },
    {
      "price": 111140,
      "amount": 41.1,
      "total": 1076
    },
    {
      "price": 111130,
      "amount": 14.3,
      "total": 1090
    },
    {
      "price": 111120,
      "amount": 14.0,
      "total": 1104
    },
    {
      "price": 111110,
      "amount": 12.7,
      "total": 1117
    },
    {
      "price": 111100,
      "amount": 49.9,
      "total": 1166
    },
    {
      "price": 111090,
      "amount": 16.3,
      "total": 1183
    },
    {
      "price": 111080,
      "amount": 24.7,
      "total": 1208
    },
    {
      "price": 111070,
      "amount": 41.2,
      "total": 1249
    },
    {
      "price": 111060,
      "amount": 51.7,
      "total": 1300
    },
    {
      "price": 111050,
      "amount": 18.5,
      "total": 1319
    },
    {
      "price": 111040,
      "amount": 20.6,
      "total": 1340
    },
    {
      "price": 111030,
      "amount": 48.5,
      "total": 1388
    },
    {
      "price": 111020,
      "amount": 22.4,
      "total": 1410
    },
    {
      "price": 111010,
      "amount": 58.6,
      "total": 1469
    },
    {
      "price": 111000,
      "amount": 75.3,
      "total": 1544
    },
    {
      "price": 110990,
      "amount": 57.0,
      "total": 1601
    },
    {
      "price": 110980,
      "amount": 13.6,
      "total": 1615
    },
    {
      "price": 110970,
      "amount": 34.4,
      "total": 1649
    },
    {
      "price": 110960,
      "amount": 14.8,
      "total": 1664
    },
    {
      "price": 110950,
      "amount": 15.0,
      "total": 1679
    },
    {
      "price": 110940,
      "amount": 10.9,
      "total": 1690
    },
    {
      "price": 110930,
      "amount": 3.8,
      "total": 1694
    },
    {
      "price": 110920,
      "amount": 9.6,
      "total": 1703
    },
    {
      "price": 110910,
      "amount": 2.8,
      "total": 1706
    },
    {
      "price": 110900,
      "amount": 4.1,
      "total": 1710
    },
    {
      "price": 110890,
      "amount": 3.3,
      "total": 1714
    },
    {
      "price": 110880,
      "amount": 10.7,
      "total": 1724
    },
    {
      "price": 110870,
      "amount": 45.8,
      "total": 1770
    },
    {
      "price": 110860,
      "amount": 7.8,
      "total": 1778
    },
    {
      "price": 110850,
      "amount": 29.8,
      "total": 1808
    },
    {
      "price": 110840,
      "amount": 1.6,
      "total": 1809
    },
    {
      "price": 110830,
      "amount": 3.5,
      "total": 1813
    },
    {
      "price": 110820,
      "amount": 3.1,
      "total": 1816
    },
    {
      "price": 110810,
      "amount": 2.0,
      "total": 1818
    },
    {
      "price": 110800,
      "amount": 14.1,
      "total": 1832
    },
    {
      "price": 110790,
      "amount": 23.6,
      "total": 1855
    },
    {
      "price": 110780,
      "amount": 7.0,
      "total": 1862
    },
    {
      "price": 110770,
      "amount": 4.3,
      "total": 1867
    },
    {
      "price": 110760,
      "amount": 2.1,
      "total": 1869
    },
    {
      "price": 110750,
      "amount": 3.4,
      "total": 1872
    },
    {
      "price": 110740,
      "amount": 2.1,
      "total": 1874
    },
    {
      "price": 110730,
      "amount": 3.1,
      "total": 1877
    },
    {
      "price": 110720,
      "amount": 31.3,
      "total": 1909
    },
    {
      "price": 110710,
      "amount": 44.3,
      "total": 1953
    },
    {
      "price": 110700,
      "amount": 41.3,
      "total": 1994
    },
    {
      "price": 110690,
      "amount": 3.7,
      "total": 1998
    },
    {
      "price": 110680,
      "amount": 4.0,
      "total": 2002
    },
    {
      "price": 110670,
      "amount": 5.2,
      "total": 2007
    },
    {
      "price": 110660,
      "amount": 15.7,
      "total": 2023
    },
    {
      "price": 110650,
      "amount": 7.3,
      "total": 2030
    },
    {
      "price": 110640,
      "amount": 54.1,
      "total": 2084
    },
    {
      "price": 110630,
      "amount": 2.8,
      "total": 2087
    },
    {
      "price": 110620,
      "amount": 2.8,
      "total": 2090
    },
    {
      "price": 110610,
      "amount": 3.4,
      "total": 2093
    },
    {
      "price": 110600,
      "amount": 19.8,
      "total": 2113
    },
    {
      "price": 110590,
      "amount": 7.1,
      "total": 2120
    },
    {
      "price": 110580,
      "amount": 4.1,
      "total": 2124
    },
    {
      "price": 110570,
      "amount": 2.5,
      "total": 2127
    },
    {
      "price": 110560,
      "amount": 2.5,
      "total": 2129
    },
    {
      "price": 110550,
      "amount": 41.5,
      "total": 2171
    },
    {
      "price": 110540,
      "amount": 3.5,
      "total": 2174
    },
    {
      "price": 110530,
      "amount": 2.6,
      "total": 2177
    },
    {
      "price": 110520,
      "amount": 16.7,
      "total": 2194
    },
    {
      "price": 110510,
      "amount": 12.9,
      "total": 2207
    },
    {
      "price": 110500,
      "amount": 14.0,
      "total": 2221
    },
    {
      "price": 110490,
      "amount": 11.8,
      "total": 2232
    },
    {
      "price": 110480,
      "amount": 0.8,
      "total": 2233
    },
    {
      "price": 110470,
      "amount": 0.9,
      "total": 2234
    },
    {
      "price": 110460,
      "amount": 0.6,
      "total": 2235
    },
    {
      "price": 110450,
      "amount": 1.6,
      "total": 2236
    },
    {
      "price": 110440,
      "amount": 0.8,
      "total": 2237
    },
    {
      "price": 110430,
      "amount": 5.3,
      "total": 2242
    },
    {
      "price": 110420,
      "amount": 15.3,
      "total": 2258
    },
    {
      "price": 110410,
      "amount": 1.7,
      "total": 2259
    },
    {
      "price": 110400,
      "amount": 3.1,
      "total": 2262
    },
    {
      "price": 110390,
      "amount": 1.2,
      "total": 2264
    },
    {
      "price": 110380,
      "amount": 3.7,
      "total": 2267
    },
    {
      "price": 110370,
      "amount": 6.4,
      "total": 2274
    },
    {
      "price": 110360,
      "amount": 13.9,
      "total": 2288
    },
    {
      "price": 110350,
      "amount": 12.8,
      "total": 2300
    },
    {
      "price": 110340,
      "amount": 2.3,
      "total": 2303
    },
    {
      "price": 110330,
      "amount": 48.5,
      "total": 2351
    },
    {
      "price": 110320,
      "amount": 8.3,
      "total": 2360
    },
    {
      "price": 110310,
      "amount": 12.3,
      "total": 2372
    },
    {
      "price": 110300,
      "amount": 1.4,
      "total": 2373
    },
    {
      "price": 110290,
      "amount": 4.7,
      "total": 2378
    },
    {
      "price": 110280,
      "amount": 4.9,
      "total": 2383
    },
    {
      "price": 110270,
      "amount": 22.5,
      "total": 2405
    },
    {
      "price": 110260,
      "amount": 5.5,
      "total": 2411
    },
    {
      "price": 110250,
      "amount": 4.4,
      "total": 2415
    },
    {
      "price": 110240,
      "amount": 3.7,
      "total": 2419
    },
    {
      "price": 110230,
      "amount": 10.4,
      "total": 2429
    },
    {
      "price": 110220,
      "amount": 5.6,
      "total": 2435
    },
    {
      "price": 110210,
      "amount": 5.5,
      "total": 2441
    },
    {
      "price": 110200,
      "amount": 15.9,
      "total": 2456
    },
    {
      "price": 110190,
      "amount": 1.8,
      "total": 2458
    },
    {
      "price": 110180,
      "amount": 12.8,
      "total": 2471
    },
    {
      "price": 110170,
      "amount": 3.2,
      "total": 2474
    },
    {
      "price": 110160,
      "amount": 7.3,
      "total": 2482
    },
    {
      "price": 110150,
      "amount": 4.4,
      "total": 2486
    },
    {
      "price": 110140,
      "amount": 1.0,
      "total": 2487
    },
    {
      "price": 110130,
      "amount": 2.6,
      "total": 2490
    },
    {
      "price": 110120,
      "amount": 3.1,
      "total": 2493
    },
    {
      "price": 110110,
      "amount": 2.6,
      "total": 2495
    },
    {
      "price": 110100,
      "amount": 7.1,
      "total": 2502
    },
    {
      "price": 110090,
      "amount": 8.9,
      "total": 2511
    },
    {
      "price": 110080,
      "amount": 3.1,
      "total": 2514
    },
    {
      "price": 110070,
      "amount": 1.4,
      "total": 2516
    },
    {
      "price": 110060,
      "amount": 3.9,
      "total": 2520
    },
    {
      "price": 110050,
      "amount": 0.9,
      "total": 2520
    },
    {
      "price": 110040,
      "amount": 6.0,
      "total": 2526
    },
    {
      "price": 110030,
      "amount": 3.1,
      "total": 2529
    },
    {
      "price": 110020,
      "amount": 4.5,
      "total": 2534
    },
    {
      "price": 110010,
      "amount": 5.2,
      "total": 2539
    },
    {
      "price": 110000,
      "amount": 35.5,
      "total": 2575
    },
    {
      "price": 109990,
      "amount": 2.7,
      "total": 2577
    },
    {
      "price": 109980,
      "amount": 3.8,
      "total": 2581
    },
    {
      "price": 109970,
      "amount": 9.2,
      "total": 2590
    },
    {
      "price": 109960,
      "amount": 8.3,
      "total": 2599
    },
    {
      "price": 109950,
      "amount": 13.7,
      "total": 2612
    },
    {
      "price": 109940,
      "amount": 6.1,
      "total": 2618
    },
    {
      "price": 109930,
      "amount": 6.9,
      "total": 2625
    },
    {
      "price": 109920,
      "amount": 6.0,
      "total": 2631
    },
    {
      "price": 109910,
      "amount": 1.0,
      "total": 2632
    },
    {
      "price": 109900,
      "amount": 4.0,
      "total": 2636
    },
    {
      "price": 109890,
      "amount": 3.3,
      "total": 2640
    },
    {
      "price": 109880,
      "amount": 5.1,
      "total": 2645
    },
    {
      "price": 109870,
      "amount": 1.9,
      "total": 2647
    },
    {
      "price": 109860,
      "amount": 1.8,
      "total": 2648
    },
    {
      "price": 109850,
      "amount": 8.1,
      "total": 2657
    },
    {
      "price": 109840,
      "amount": 8.0,
      "total": 2665
    },
    {
      "price": 109830,
      "amount": 2.1,
      "total": 2667
    },
    {
      "price": 109820,
      "amount": 6.8,
      "total": 2673
    },
    {
      "price": 109810,
      "amount": 20.3,
      "total": 2694
    },
    {
      "price": 109800,
      "amount": 24.6,
      "total": 2718
    },
    {
      "price": 109790,
      "amount": 14.5,
      "total": 2733
    },
    {
      "price": 109780,
      "amount": 11.5,
      "total": 2744
    },
    {
      "price": 109770,
      "amount": 13.2,
      "total": 2758
    },
    {
      "price": 109760,
      "amount": 12.7,
      "total": 2770
    },
    {
      "price": 109750,
      "amount": 2.3,
      "total": 2773
    },
    {
      "price": 109740,
      "amount": 4.3,
      "total": 2777
    },
    {
      "price": 109730,
      "amount": 2.7,
      "total": 2780
    },
    {
      "price": 109720,
      "amount": 4.9,
      "total": 2785
    },
    {
      "price": 109710,
      "amount": 3.0,
      "total": 2788
    },
    {
      "price": 109700,
      "amount": 6.6,
      "total": 2794
    },
    {
      "price": 109690,
      "amount": 2.4,
      "total": 2797
    },
    {
      "price": 109680,
      "amount": 4.9,
      "total": 2801
    },
    {
      "price": 109670,
      "amount": 1.1,
      "total": 2803
    },
    {
      "price": 109660,
      "amount": 2.7,
      "total": 2805
    },
    {
      "price": 109650,
      "amount": 4.5,
      "total": 2810
    },
    {
      "price": 109640,
      "amount": 2.0,
      "total": 2812
    },
    {
      "price": 109630,
      "amount": 0.5,
      "total": 2812
    },
    {
      "price": 109620,
      "amount": 5.8,
      "total": 2818
    },
    {
      "price": 109610,
      "amount": 3.2,
      "total": 2821
    },
    {
      "price": 109600,
      "amount": 14.8,
      "total": 2836
    },
    {
      "price": 109590,
      "amount": 7.4,
      "total": 2844
    },
    {
      "price": 109580,
      "amount": 15.3,
      "total": 2859
    },
    {
      "price": 109570,
      "amount": 9.0,
      "total": 2868
    },
    {
      "price": 109560,
      "amount": 6.1,
      "total": 2874
    },
    {
      "price": 109550,
      "amount": 12.9,
      "total": 2887
    },
    {
      "price": 109540,
      "amount": 7.5,
      "total": 2895
    },
    {
      "price": 109530,
      "amount": 5.6,
      "total": 2900
    },
    {
      "price": 109520,
      "amount": 1.6,
      "total": 2902
    },
    {
      "price": 109510,
      "amount": 6.1,
      "total": 2908
    },
    {
      "price": 109500,
      "amount": 23.8,
      "total": 2932
    },
    {
      "price": 109490,
      "amount": 4.7,
      "total": 2936
    },
    {
      "price": 109480,
      "amount": 2.2,
      "total": 2939
    },
    {
      "price": 109470,
      "amount": 10.2,
      "total": 2949
    },
    {
      "price": 109460,
      "amount": 17.6,
      "total": 2966
    },
    {
      "price": 109450,
      "amount": 28.5,
      "total": 2995
    },
    {
      "price": 109440,
      "amount": 5.0,
      "total": 3000
    },
    {
      "price": 109430,
      "amount": 14.0,
      "total": 3014
    },
    {
      "price": 109420,
      "amount": 6.9,
      "total": 3021
    },
    {
      "price": 109410,
      "amount": 4.4,
      "total": 3025
    },
    {
      "price": 109400,
      "amount": 26.0,
      "total": 3051
    },
    {
      "price": 109390,
      "amount": 4.1,
      "total": 3055
    },
    {
      "price": 109380,
      "amount": 11.8,
      "total": 3067
    },
    {
      "price": 109370,
      "amount": 6.7,
      "total": 3074
    },
    {
      "price": 109360,
      "amount": 7.6,
      "total": 3081
    },
    {
      "price": 109350,
      "amount": 18.5,
      "total": 3100
    },
    {
      "price": 109340,
      "amount": 4.1,
      "total": 3104
    },
    {
      "price": 109330,
      "amount": 8.0,
      "total": 3112
    },
    {
      "price": 109320,
      "amount": 1.5,
      "total": 3114
    },
    {
      "price": 109310,
      "amount": 1.0,
      "total": 3115
    },
    {
      "price": 109300,
      "amount": 14.1,
      "total": 3129
    },
    {
      "price": 109290,
      "amount": 2.2,
      "total": 3131
    },
    {
      "price": 109280,
      "amount": 4.0,
      "total": 3135
    },
    {
      "price": 109270,
      "amount": 18.6,
      "total": 3153
    },
    {
      "price": 109260,
      "amount": 6.9,
      "total": 3160
    },
    {
      "price": 109250,
      "amount": 6.1,
      "total": 3166
    },
    {
      "price": 109240,
      "amount": 1.9,
      "total": 3168
    },
    {
      "price": 109230,
      "amount": 1.4,
      "total": 3170
    },
    {
      "price": 109220,
      "amount": 9.7,
      "total": 3179
    },
    {
      "price": 109210,
      "amount": 3.5,
      "total": 3183
    },
    {
      "price": 109200,
      "amount": 28.8,
      "total": 3211
    },
    {
      "price": 109190,
      "amount": 3.3,
      "total": 3215
    },
    {
      "price": 109180,
      "amount": 3.4,
      "total": 3218
    },
    {
      "price": 109170,
      "amount": 2.0,
      "total": 3220
    },
    {
      "price": 109160,
      "amount": 1.9,
      "total": 3222
    },
    {
      "price": 109150,
      "amount": 4.3,
      "total": 3226
    },
    {
      "price": 109140,
      "amount": 0.8,
      "total": 3227
    },
    {
      "price": 109130,
      "amount": 1.7,
      "total": 3229
    },
    {
      "price": 109120,
      "amount": 1.0,
      "total": 3230
    },
    {
      "price": 109110,
      "amount": 2.2,
      "total": 3232
    },
    {
      "price": 109100,
      "amount": 8.8,
      "total": 3241
    },
    {
      "price": 109090,
      "amount": 1.6,
      "total": 3242
    },
    {
      "price": 109080,
      "amount": 1.1,
      "total": 3243
    },
    {
      "price": 109070,
      "amount": 3.9,
      "total": 3247
    },
    {
      "price": 109060,
      "amount": 1.2,
      "total": 3249
    },
    {
      "price": 109050,
      "amount": 3.4,
      "total": 3252
    }
  ],
  "asks": [
    {
      "price": 113800,
      "amount": 16.9,
      "total": 3672
    },
    {
      "price": 113790,
      "amount": 0.9,
      "total": 3655
    },
    {
      "price": 113780,
      "amount": 4.1,
      "total": 3654
    },
    {
      "price": 113770,
      "amount": 4.3,
      "total": 3650
    },
    {
      "price": 113760,
      "amount": 1.1,
      "total": 3646
    },
    {
      "price": 113750,
      "amount": 2.6,
      "total": 3645
    },
    {
      "price": 113740,
      "amount": 1.7,
      "total": 3642
    },
    {
      "price": 113730,
      "amount": 2.5,
      "total": 3640
    },
    {
      "price": 113720,
      "amount": 13.2,
      "total": 3638
    },
    {
      "price": 113710,
      "amount": 1.4,
      "total": 3625
    },
    {
      "price": 113700,
      "amount": 5.7,
      "total": 3623
    },
    {
      "price": 113690,
      "amount": 3.6,
      "total": 3618
    },
    {
      "price": 113680,
      "amount": 1.8,
      "total": 3614
    },
    {
      "price": 113670,
      "amount": 9.2,
      "total": 3612
    },
    {
      "price": 113660,
      "amount": 0.5,
      "total": 3603
    },
    {
      "price": 113650,
      "amount": 2.8,
      "total": 3603
    },
    {
      "price": 113640,
      "amount": 0.7,
      "total": 3600
    },
    {
      "price": 113630,
      "amount": 2.6,
      "total": 3599
    },
    {
      "price": 113620,
      "amount": 1.2,
      "total": 3596
    },
    {
      "price": 113610,
      "amount": 1.3,
      "total": 3595
    },
    {
      "price": 113600,
      "amount": 10.0,
      "total": 3594
    },
    {
      "price": 113590,
      "amount": 1.6,
      "total": 3584
    },
    {
      "price": 113580,
      "amount": 1.8,
      "total": 3582
    },
    {
      "price": 113570,
      "amount": 2.3,
      "total": 3580
    },
    {
      "price": 113560,
      "amount": 1.9,
      "total": 3578
    },
    {
      "price": 113550,
      "amount": 2.9,
      "total": 3576
    },
    {
      "price": 113540,
      "amount": 1.7,
      "total": 3573
    },
    {
      "price": 113530,
      "amount": 2.7,
      "total": 3572
    },
    {
      "price": 113520,
      "amount": 14.9,
      "total": 3569
    },
    {
      "price": 113510,
      "amount": 5.2,
      "total": 3554
    },
    {
      "price": 113500,
      "amount": 42.7,
      "total": 3549
    },
    {
      "price": 113490,
      "amount": 7.2,
      "total": 3506
    },
    {
      "price": 113480,
      "amount": 7.0,
      "total": 3499
    },
    {
      "price": 113470,
      "amount": 4.6,
      "total": 3492
    },
    {
      "price": 113460,
      "amount": 15.5,
      "total": 3487
    },
    {
      "price": 113450,
      "amount": 53.0,
      "total": 3472
    },
    {
      "price": 113440,
      "amount": 2.2,
      "total": 3419
    },
    {
      "price": 113430,
      "amount": 10.0,
      "total": 3417
    },
    {
      "price": 113420,
      "amount": 2.6,
      "total": 3407
    },
    {
      "price": 113410,
      "amount": 39.5,
      "total": 3404
    },
    {
      "price": 113400,
      "amount": 18.5,
      "total": 3364
    },
    {
      "price": 113390,
      "amount": 5.6,
      "total": 3346
    },
    {
      "price": 113380,
      "amount": 12.6,
      "total": 3340
    },
    {
      "price": 113370,
      "amount": 8.2,
      "total": 3328
    },
    {
      "price": 113360,
      "amount": 12.9,
      "total": 3320
    },
    {
      "price": 113350,
      "amount": 13.6,
      "total": 3307
    },
    {
      "price": 113340,
      "amount": 19.7,
      "total": 3293
    },
    {
      "price": 113330,
      "amount": 3.0,
      "total": 3273
    },
    {
      "price": 113320,
      "amount": 8.8,
      "total": 3270
    },
    {
      "price": 113310,
      "amount": 1.2,
      "total": 3262
    },
    {
      "price": 113300,
      "amount": 6.1,
      "total": 3260
    },
    {
      "price": 113290,
      "amount": 8.9,
      "total": 3254
    },
    {
      "price": 113280,
      "amount": 7.5,
      "total": 3245
    },
    {
      "price": 113270,
      "amount": 9.6,
      "total": 3238
    },
    {
      "price": 113260,
      "amount": 7.5,
      "total": 3228
    },
    {
      "price": 113250,
      "amount": 10.6,
      "total": 3221
    },
    {
      "price": 113240,
      "amount": 5.4,
      "total": 3210
    },
    {
      "price": 113230,
      "amount": 18.5,
      "total": 3205
    },
    {
      "price": 113220,
      "amount": 1.9,
      "total": 3186
    },
    {
      "price": 113210,
      "amount": 2.4,
      "total": 3184
    },
    {
      "price": 113200,
      "amount": 9.5,
      "total": 3182
    },
    {
      "price": 113190,
      "amount": 3.4,
      "total": 3173
    },
    {
      "price": 113180,
      "amount": 1.4,
      "total": 3169
    },
    {
      "price": 113170,
      "amount": 6.1,
      "total": 3168
    },
    {
      "price": 113160,
      "amount": 9.5,
      "total": 3162
    },
    {
      "price": 113150,
      "amount": 1.2,
      "total": 3152
    },
    {
      "price": 113140,
      "amount": 3.0,
      "total": 3151
    },
    {
      "price": 113130,
      "amount": 4.3,
      "total": 3148
    },
    {
      "price": 113120,
      "amount": 21.8,
      "total": 3143
    },
    {
      "price": 113110,
      "amount": 3.3,
      "total": 3122
    },
    {
      "price": 113100,
      "amount": 7.1,
      "total": 3118
    },
    {
      "price": 113090,
      "amount": 6.4,
      "total": 3111
    },
    {
      "price": 113080,
      "amount": 4.1,
      "total": 3105
    },
    {
      "price": 113070,
      "amount": 5.3,
      "total": 3101
    },
    {
      "price": 113060,
      "amount": 10.8,
      "total": 3095
    },
    {
      "price": 113050,
      "amount": 13.6,
      "total": 3085
    },
    {
      "price": 113040,
      "amount": 10.1,
      "total": 3071
    },
    {
      "price": 113030,
      "amount": 22.2,
      "total": 3061
    },
    {
      "price": 113020,
      "amount": 8.6,
      "total": 3039
    },
    {
      "price": 113010,
      "amount": 4.7,
      "total": 3030
    },
    {
      "price": 113000,
      "amount": 57.0,
      "total": 3025
    },
    {
      "price": 112990,
      "amount": 7.6,
      "total": 2968
    },
    {
      "price": 112980,
      "amount": 4.7,
      "total": 2961
    },
    {
      "price": 112970,
      "amount": 5.7,
      "total": 2956
    },
    {
      "price": 112960,
      "amount": 1.0,
      "total": 2950
    },
    {
      "price": 112950,
      "amount": 3.7,
      "total": 2949
    },
    {
      "price": 112940,
      "amount": 4.5,
      "total": 2946
    },
    {
      "price": 112930,
      "amount": 2.6,
      "total": 2941
    },
    {
      "price": 112920,
      "amount": 1.9,
      "total": 2939
    },
    {
      "price": 112910,
      "amount": 3.5,
      "total": 2937
    },
    {
      "price": 112900,
      "amount": 11.1,
      "total": 2933
    },
    {
      "price": 112890,
      "amount": 29.0,
      "total": 2922
    },
    {
      "price": 112880,
      "amount": 15.0,
      "total": 2893
    },
    {
      "price": 112870,
      "amount": 4.4,
      "total": 2878
    },
    {
      "price": 112860,
      "amount": 25.5,
      "total": 2874
    },
    {
      "price": 112850,
      "amount": 9.5,
      "total": 2848
    },
    {
      "price": 112840,
      "amount": 5.7,
      "total": 2839
    },
    {
      "price": 112830,
      "amount": 4.1,
      "total": 2833
    },
    {
      "price": 112820,
      "amount": 7.4,
      "total": 2829
    },
    {
      "price": 112810,
      "amount": 10.3,
      "total": 2822
    },
    {
      "price": 112800,
      "amount": 18.8,
      "total": 2811
    },
    {
      "price": 112790,
      "amount": 4.0,
      "total": 2792
    },
    {
      "price": 112780,
      "amount": 3.4,
      "total": 2789
    },
    {
      "price": 112770,
      "amount": 4.5,
      "total": 2785
    },
    {
      "price": 112760,
      "amount": 1.7,
      "total": 2781
    },
    {
      "price": 112750,
      "amount": 24.0,
      "total": 2779
    },
    {
      "price": 112740,
      "amount": 2.9,
      "total": 2755
    },
    {
      "price": 112730,
      "amount": 8.3,
      "total": 2752
    },
    {
      "price": 112720,
      "amount": 1.8,
      "total": 2744
    },
    {
      "price": 112710,
      "amount": 2.0,
      "total": 2742
    },
    {
      "price": 112700,
      "amount": 7.8,
      "total": 2740
    },
    {
      "price": 112690,
      "amount": 2.4,
      "total": 2732
    },
    {
      "price": 112680,
      "amount": 2.3,
      "total": 2730
    },
    {
      "price": 112670,
      "amount": 20.5,
      "total": 2727
    },
    {
      "price": 112660,
      "amount": 3.9,
      "total": 2707
    },
    {
      "price": 112650,
      "amount": 9.2,
      "total": 2703
    },
    {
      "price": 112640,
      "amount": 2.9,
      "total": 2694
    },
    {
      "price": 112630,
      "amount": 2.6,
      "total": 2691
    },
    {
      "price": 112620,
      "amount": 5.1,
      "total": 2688
    },
    {
      "price": 112610,
      "amount": 4.9,
      "total": 2683
    },
    {
      "price": 112600,
      "amount": 10.1,
      "total": 2678
    },
    {
      "price": 112590,
      "amount": 2.1,
      "total": 2668
    },
    {
      "price": 112580,
      "amount": 1.9,
      "total": 2666
    },
    {
      "price": 112570,
      "amount": 3.6,
      "total": 2664
    },
    {
      "price": 112560,
      "amount": 6.3,
      "total": 2661
    },
    {
      "price": 112550,
      "amount": 2.1,
      "total": 2654
    },
    {
      "price": 112540,
      "amount": 1.1,
      "total": 2652
    },
    {
      "price": 112530,
      "amount": 1.3,
      "total": 2651
    },
    {
      "price": 112520,
      "amount": 20.8,
      "total": 2650
    },
    {
      "price": 112510,
      "amount": 2.2,
      "total": 2629
    },
    {
      "price": 112500,
      "amount": 66.9,
      "total": 2627
    },
    {
      "price": 112490,
      "amount": 7.5,
      "total": 2560
    },
    {
      "price": 112480,
      "amount": 8.0,
      "total": 2552
    },
    {
      "price": 112470,
      "amount": 65.2,
      "total": 2544
    },
    {
      "price": 112460,
      "amount": 7.5,
      "total": 2479
    },
    {
      "price": 112450,
      "amount": 6.2,
      "total": 2472
    },
    {
      "price": 112440,
      "amount": 0.9,
      "total": 2465
    },
    {
      "price": 112430,
      "amount": 0.7,
      "total": 2465
    },
    {
      "price": 112420,
      "amount": 16.3,
      "total": 2464
    },
    {
      "price": 112410,
      "amount": 3.1,
      "total": 2447
    },
    {
      "price": 112400,
      "amount": 5.7,
      "total": 2444
    },
    {
      "price": 112390,
      "amount": 8.9,
      "total": 2439
    },
    {
      "price": 112380,
      "amount": 0.2,
      "total": 2430
    },
    {
      "price": 112370,
      "amount": 12.0,
      "total": 2430
    },
    {
      "price": 112360,
      "amount": 1.0,
      "total": 2418
    },
    {
      "price": 112350,
      "amount": 2.7,
      "total": 2417
    },
    {
      "price": 112340,
      "amount": 1.8,
      "total": 2414
    },
    {
      "price": 112330,
      "amount": 3.3,
      "total": 2412
    },
    {
      "price": 112320,
      "amount": 1.4,
      "total": 2409
    },
    {
      "price": 112310,
      "amount": 3.1,
      "total": 2407
    },
    {
      "price": 112300,
      "amount": 166.0,
      "total": 2404
    },
    {
      "price": 112290,
      "amount": 4.5,
      "total": 2238
    },
    {
      "price": 112280,
      "amount": 3.6,
      "total": 2234
    },
    {
      "price": 112270,
      "amount": 2.2,
      "total": 2230
    },
    {
      "price": 112260,
      "amount": 9.3,
      "total": 2228
    },
    {
      "price": 112250,
      "amount": 7.0,
      "total": 2219
    },
    {
      "price": 112240,
      "amount": 53.0,
      "total": 2212
    },
    {
      "price": 112230,
      "amount": 18.2,
      "total": 2159
    },
    {
      "price": 112220,
      "amount": 50.9,
      "total": 2141
    },
    {
      "price": 112210,
      "amount": 3.5,
      "total": 2090
    },
    {
      "price": 112200,
      "amount": 19.1,
      "total": 2086
    },
    {
      "price": 112190,
      "amount": 13.9,
      "total": 2067
    },
    {
      "price": 112180,
      "amount": 42.5,
      "total": 2053
    },
    {
      "price": 112170,
      "amount": 2.6,
      "total": 2011
    },
    {
      "price": 112160,
      "amount": 2.9,
      "total": 2008
    },
    {
      "price": 112150,
      "amount": 9.2,
      "total": 2005
    },
    {
      "price": 112140,
      "amount": 2.6,
      "total": 1996
    },
    {
      "price": 112130,
      "amount": 4.2,
      "total": 1993
    },
    {
      "price": 112120,
      "amount": 8.2,
      "total": 1989
    },
    {
      "price": 112110,
      "amount": 7.0,
      "total": 1981
    },
    {
      "price": 112100,
      "amount": 12.0,
      "total": 1974
    },
    {
      "price": 112090,
      "amount": 9.8,
      "total": 1962
    },
    {
      "price": 112080,
      "amount": 5.5,
      "total": 1952
    },
    {
      "price": 112070,
      "amount": 54.9,
      "total": 1947
    },
    {
      "price": 112060,
      "amount": 16.1,
      "total": 1892
    },
    {
      "price": 112050,
      "amount": 45.5,
      "total": 1876
    },
    {
      "price": 112040,
      "amount": 4.8,
      "total": 1830
    },
    {
      "price": 112030,
      "amount": 2.6,
      "total": 1825
    },
    {
      "price": 112020,
      "amount": 3.6,
      "total": 1823
    },
    {
      "price": 112010,
      "amount": 32.4,
      "total": 1819
    },
    {
      "price": 112000,
      "amount": 112.4,
      "total": 1787
    },
    {
      "price": 111990,
      "amount": 7.2,
      "total": 1674
    },
    {
      "price": 111980,
      "amount": 4.3,
      "total": 1667
    },
    {
      "price": 111970,
      "amount": 4.1,
      "total": 1663
    },
    {
      "price": 111960,
      "amount": 3.9,
      "total": 1659
    },
    {
      "price": 111950,
      "amount": 42.3,
      "total": 1655
    },
    {
      "price": 111940,
      "amount": 26.0,
      "total": 1613
    },
    {
      "price": 111930,
      "amount": 14.6,
      "total": 1587
    },
    {
      "price": 111920,
      "amount": 10.0,
      "total": 1572
    },
    {
      "price": 111910,
      "amount": 12.1,
      "total": 1562
    },
    {
      "price": 111900,
      "amount": 18.1,
      "total": 1550
    },
    {
      "price": 111890,
      "amount": 19.5,
      "total": 1532
    },
    {
      "price": 111880,
      "amount": 27.0,
      "total": 1513
    },
    {
      "price": 111870,
      "amount": 13.6,
      "total": 1485
    },
    {
      "price": 111860,
      "amount": 12.4,
      "total": 1472
    },
    {
      "price": 111850,
      "amount": 6.3,
      "total": 1460
    },
    {
      "price": 111840,
      "amount": 10.9,
      "total": 1453
    },
    {
      "price": 111830,
      "amount": 53.0,
      "total": 1442
    },
    {
      "price": 111820,
      "amount": 11.8,
      "total": 1389
    },
    {
      "price": 111810,
      "amount": 43.4,
      "total": 1378
    },
    {
      "price": 111800,
      "amount": 39.2,
      "total": 1334
    },
    {
      "price": 111790,
      "amount": 16.1,
      "total": 1295
    },
    {
      "price": 111780,
      "amount": 90.5,
      "total": 1279
    },
    {
      "price": 111770,
      "amount": 74.1,
      "total": 1188
    },
    {
      "price": 111760,
      "amount": 16.1,
      "total": 1114
    },
    {
      "price": 111750,
      "amount": 36.2,
      "total": 1098
    },
    {
      "price": 111740,
      "amount": 40.5,
      "total": 1062
    },
    {
      "price": 111730,
      "amount": 16.7,
      "total": 1022
    },
    {
      "price": 111720,
      "amount": 29.3,
      "total": 1005
    },
    {
      "price": 111710,
      "amount": 27.2,
      "total": 975.6
    },
    {
      "price": 111700,
      "amount": 24.5,
      "total": 948.4
    },
    {
      "price": 111690,
      "amount": 79.6,
      "total": 923.8
    },
    {
      "price": 111680,
      "amount": 20.8,
      "total": 844.2
    },
    {
      "price": 111670,
      "amount": 81.4,
      "total": 823.4
    },
    {
      "price": 111660,
      "amount": 41.0,
      "total": 742.1
    },
    {
      "price": 111650,
      "amount": 13.8,
      "total": 701.0
    },
    {
      "price": 111640,
      "amount": 24.7,
      "total": 687.2
    },
    {
      "price": 111630,
      "amount": 49.1,
      "total": 662.5
    },
    {
      "price": 111620,
      "amount": 55.8,
      "total": 613.5
    },
    {
      "price": 111610,
      "amount": 21.8,
      "total": 557.7
    },
    {
      "price": 111600,
      "amount": 25.7,
      "total": 535.8
    },
    {
      "price": 111590,
      "amount": 37.9,
      "total": 510.2
    },
    {
      "price": 111580,
      "amount": 33.0,
      "total": 472.3
    },
    {
      "price": 111570,
      "amount": 41.5,
      "total": 439.3
    },
    {
      "price": 111560,
      "amount": 40.0,
      "total": 397.8
    },
    {
      "price": 111550,
      "amount": 36.8,
      "total": 357.8
    },
    {
      "price": 111540,
      "amount": 31.8,
      "total": 321.0
    },
    {
      "price": 111530,
      "amount": 12.0,
      "total": 289.3
    },
    {
      "price": 111520,
      "amount": 19.1,
      "total": 277.3
    },
    {
      "price": 111510,
      "amount": 17.7,
      "total": 258.2
    },
    {
      "price": 111500,
      "amount": 30.6,
      "total": 240.5
    },
    {
      "price": 111490,
      "amount": 33.3,
      "total": 209.9
    },
    {
      "price": 111480,
      "amount": 38.2,
      "total": 176.6
    },
    {
      "price": 111470,
      "amount": 21.8,
      "total": 138.4
    },
    {
      "price": 111460,
      "amount": 22.2,
      "total": 116.6
    },
    {
      "price": 111450,
      "amount": 23.9,
      "total": 94.3
    },
    {
      "price": 111440,
      "amount": 22.5,
      "total": 70.4
    },
    {
      "price": 111430,
      "amount": 29.8,
      "total": 47.9
    },
    {
      "price": 111420,
      "amount": 15.5,
      "total": 18.1
    },
    {
      "price": 111410,
      "amount": 2.7,
      "total": 2.7
    }
  ]
}